[{"id":"5762b5fd315cde9c16ce41dc","title":"Find gratitude in life especially during a tragedy.","bigIdea":"Gratitude","essentialQuestion":"How can gratitude change my entire perspective on tragedy?","createdAt":"2016-06-16T14:21:49.076Z","updatedAt":"2016-06-16T14:21:49.076Z","user":{"id":"57616a22ee7e776c02f36586","picture":"https://gravatar.com/avatar/e0675d18aada9669f5db696e50f2f0d0?d=identicon"},"users":["57616a22ee7e776c02f36586"],"photo":{"large":{"height":"683","src":"https://farm6.staticflickr.com/5158/14437506753_4f9e839c33_b.jpg","width":"1024"},"medium":{"height":"333","src":"https://farm6.staticflickr.com/5158/14437506753_4f9e839c33.jpg","width":"500"},"owner":"Puno3000","small":{"height":"160","src":"https://farm6.staticflickr.com/5158/14437506753_4f9e839c33_m.jpg","width":"240"},"url":"https://www.flickr.com/photos/52782782@N08/14437506753"},"tags":[{"id":"5762b5fe315cde9c16ce41dd","name":"Tuesday"},{"id":"5762b5fe315cde9c16ce41de","name":"Mitch Albom"},{"id":"5762b5fe315cde9c16ce41df","name":"Sugababes"},{"id":"5762b5fe315cde9c16ce41e0","name":"Debut albums"},{"id":"5762b5fe315cde9c16ce41e1","name":"Gratitude"},{"id":"5762b5fe315cde9c16ce41e2","name":"tragedy"},{"id":"5762b5fe315cde9c16ce41e3","name":"gratitude"},{"id":"5762b5fe315cde9c16ce41e4","name":"entire perspective"},{"id":"5762b5fe315cde9c16ce41e5","name":"novel Tuesdays"},{"id":"5762b5fe315cde9c16ce41e6","name":"challenge"},{"id":"5762b5fe315cde9c16ce41e7","name":"people"},{"id":"5762b5fe315cde9c16ce41e8","name":"way"},{"id":"5762b5fe315cde9c16ce41e9","name":"Morrie"},{"id":"5762b5fe315cde9c16ce41ea","name":"darkness"},{"id":"5762b5fe315cde9c16ce41eb","name":"conjunction"},{"id":"5762b5fe315cde9c16ce41ec","name":"attitude"},{"id":"5762b5fe315cde9c16ce41ed","name":"question"},{"id":"5762b5fe315cde9c16ce41ee","name":"life"},{"id":"5762b5fe315cde9c16ce41ef","name":"light"},{"id":"5762b5fe315cde9c16ce41f0","name":"beauty"},{"id":"5762b5fe315cde9c16ce41f1","name":"lives"}],"guides":[]},{"id":"5762b5fd315cde9c16dsadc","title":"Find gratitude in life especially during a tragedy.","bigIdea":"Gratitude","essentialQuestion":"How can gratitude change jdsajd sahdj hsa as my entire perspective on tragedy?","createdAt":"2016-06-16T14:21:49.076Z","updatedAt":"2016-06-16T14:21:49.076Z","user":{"id":"57616a22ee7e776c02f36586","picture":"https://gravatar.com/avatar/e0675d18aada9669f5db696e50f2f0d0?d=identicon"},"users":["57616a22ee7e776c02f36586"],"photo":{"large":{"height":"683","src":"https://farm6.staticflickr.com/5158/14437506753_4f9e839c33_b.jpg","width":"1024"},"medium":{"height":"333","src":"https://farm6.staticflickr.com/5158/14437506753_4f9e839c33.jpg","width":"500"},"owner":"Puno3000","small":{"height":"160","src":"https://farm6.staticflickr.com/5158/14437506753_4f9e839c33_m.jpg","width":"240"},"url":"https://www.flickr.com/photos/52782782@N08/14437506753"},"tags":[{"id":"5762b5fe315cde9c16ce41dd","name":"Tuesdays with Morrie"},{"id":"5762b5fe315cde9c16ce41de","name":"Mitch Albom"},{"id":"5762b5fe315cde9c16ce41df","name":"Sugababes"},{"id":"5762b5fe315cde9c16ce41e0","name":"Debut albums"},{"id":"5762b5fe315cde9c16ce41e1","name":"Gratitude"},{"id":"5762b5fe315cde9c16ce41e2","name":"tragedy"},{"id":"5762b5fe315cde9c16ce41e3","name":"gratitude"},{"id":"5762b5fe315cde9c16ce41e4","name":"entire perspective"},{"id":"5762b5fe315cde9c16ce41e5","name":"novel Tuesdays"},{"id":"5762b5fe315cde9c16ce41e6","name":"challenge"},{"id":"5762b5fe315cde9c16ce41e7","name":"people"},{"id":"5762b5fe315cde9c16ce41e8","name":"way"},{"id":"5762b5fe315cde9c16ce41e9","name":"Morrie"},{"id":"5762b5fe315cde9c16ce41ea","name":"darkness"},{"id":"5762b5fe315cde9c16ce41eb","name":"conjunction"},{"id":"5762b5fe315cde9c16ce41ec","name":"attitude"},{"id":"5762b5fe315cde9c16ce41ed","name":"question"},{"id":"5762b5fe315cde9c16ce41ee","name":"life"},{"id":"5762b5fe315cde9c16ce41ef","name":"light"},{"id":"5762b5fe315cde9c16ce41f0","name":"beauty"},{"id":"5762b5fe315cde9c16ce41f1","name":"lives"}],"guides":[]},{"id":"5762b5fd315cde9c16ce41fd","title":"Find gratitude in life especially during a tragedy.","bigIdea":"Gratitude","essentialQuestion":"How can jdsakljdklasjdl gratitude change my entire perspective on tragedy?","createdAt":"2016-06-16T14:21:49.076Z","updatedAt":"2016-06-16T14:21:49.076Z","user":{"id":"57616a22ee7e776c02f36586","picture":"https://gravatar.com/avatar/e0675d18aada9669f5db696e50f2f0d0?d=identicon"},"users":["57616a22ee7e776c02f36586"],"photo":{"large":{"height":"683","src":"https://farm6.staticflickr.com/5158/14437506753_4f9e839c33_b.jpg","width":"1024"},"medium":{"height":"333","src":"https://farm6.staticflickr.com/5158/14437506753_4f9e839c33.jpg","width":"500"},"owner":"Puno3000","small":{"height":"160","src":"https://farm6.staticflickr.com/5158/14437506753_4f9e839c33_m.jpg","width":"240"},"url":"https://www.flickr.com/photos/52782782@N08/14437506753"},"tags":[{"id":"5762b5fe315cde9c16ce41dd","name":"Tuesdays with Morrie"},{"id":"5762b5fe315cde9c16ce41de","name":"Mitch Albom"},{"id":"5762b5fe315cde9c16ce41df","name":"Sugababes"},{"id":"5762b5fe315cde9c16ce41e0","name":"Debut albums"},{"id":"5762b5fe315cde9c16ce41e1","name":"Gratitude"},{"id":"5762b5fe315cde9c16ce41e2","name":"tragedy"},{"id":"5762b5fe315cde9c16ce41e3","name":"gratitude"},{"id":"5762b5fe315cde9c16ce41e4","name":"entire perspective"},{"id":"5762b5fe315cde9c16ce41e5","name":"novel Tuesdays"},{"id":"5762b5fe315cde9c16ce41e6","name":"challenge"},{"id":"5762b5fe315cde9c16ce41e7","name":"people"},{"id":"5762b5fe315cde9c16ce41e8","name":"way"},{"id":"5762b5fe315cde9c16ce41e9","name":"Morrie"},{"id":"5762b5fe315cde9c16ce41ea","name":"darkness"},{"id":"5762b5fe315cde9c16ce41eb","name":"conjunction"},{"id":"5762b5fe315cde9c16ce41ec","name":"attitude"},{"id":"5762b5fe315cde9c16ce41ed","name":"question"},{"id":"5762b5fe315cde9c16ce41ee","name":"life"},{"id":"5762b5fe315cde9c16ce41ef","name":"light"},{"id":"5762b5fe315cde9c16ce41f0","name":"beauty"},{"id":"5762b5fe315cde9c16ce41f1","name":"lives"}],"guides":[]},{"id":"5762b5fd315cde9caasce41dc","title":"Find gratitude in life especially during a tragedy.","bigIdea":"Gratitude","essentialQuestion":"How can on tragedy?","createdAt":"2016-06-16T14:21:49.076Z","updatedAt":"2016-06-16T14:21:49.076Z","user":{"id":"57616a22ee7e776c02f36586","picture":"https://gravatar.com/avatar/e0675d18aada9669f5db696e50f2f0d0?d=identicon"},"users":["57616a22ee7e776c02f36586"],"photo":{"large":{"height":"683","src":"https://farm6.staticflickr.com/5158/14437506753_4f9e839c33_b.jpg","width":"1024"},"medium":{"height":"333","src":"https://farm6.staticflickr.com/5158/14437506753_4f9e839c33.jpg","width":"500"},"owner":"Puno3000","small":{"height":"160","src":"https://farm6.staticflickr.com/5158/14437506753_4f9e839c33_m.jpg","width":"240"},"url":"https://www.flickr.com/photos/52782782@N08/14437506753"},"tags":[{"id":"5762b5fe315cde9c16ce41dd","name":"Tuesdays with Morrie"},{"id":"5762b5fe315cde9c16ce41de","name":"Mitch Albom"},{"id":"5762b5fe315cde9c16ce41df","name":"Sugababes"},{"id":"5762b5fe315cde9c16ce41e0","name":"Debut albums"},{"id":"5762b5fe315cde9c16ce41e1","name":"Gratitude"},{"id":"5762b5fe315cde9c16ce41e2","name":"tragedy"},{"id":"5762b5fe315cde9c16ce41e3","name":"gratitude"},{"id":"5762b5fe315cde9c16ce41e4","name":"entire perspective"},{"id":"5762b5fe315cde9c16ce41e5","name":"novel Tuesdays"},{"id":"5762b5fe315cde9c16ce41e6","name":"challenge"},{"id":"5762b5fe315cde9c16ce41e7","name":"people"},{"id":"5762b5fe315cde9c16ce41e8","name":"way"},{"id":"5762b5fe315cde9c16ce41e9","name":"Morrie"},{"id":"5762b5fe315cde9c16ce41ea","name":"darkness"},{"id":"5762b5fe315cde9c16ce41eb","name":"conjunction"},{"id":"5762b5fe315cde9c16ce41ec","name":"attitude"},{"id":"5762b5fe315cde9c16ce41ed","name":"question"},{"id":"5762b5fe315cde9c16ce41ee","name":"life"},{"id":"5762b5fe315cde9c16ce41ef","name":"light"},{"id":"5762b5fe315cde9c16ce41f0","name":"beauty"},{"id":"5762b5fe315cde9c16ce41f1","name":"lives"}],"guides":[]},{"id":"5762b5fd315cd41dc","title":"Find gratitude in life especially during a tragedy.","bigIdea":"Gratitude","essentialQuestion":"How can gratitude change my entire perspective on tragedy?","createdAt":"2016-06-16T14:21:49.076Z","updatedAt":"2016-06-16T14:21:49.076Z","user":{"id":"57616a22ee7e776c02f36586","picture":"https://gravatar.com/avatar/e0675d18aada9669f5db696e50f2f0d0?d=identicon"},"users":["57616a22ee7e776c02f36586"],"photo":{"large":{"height":"683","src":"https://farm6.staticflickr.com/5158/14437506753_4f9e839c33_b.jpg","width":"1024"},"medium":{"height":"333","src":"https://farm6.staticflickr.com/5158/14437506753_4f9e839c33.jpg","width":"500"},"owner":"Puno3000","small":{"height":"160","src":"https://farm6.staticflickr.com/5158/14437506753_4f9e839c33_m.jpg","width":"240"},"url":"https://www.flickr.com/photos/52782782@N08/14437506753"},"tags":[{"id":"5762b5fe315cde9c16ce41dd","name":"Tuesdays with Morrie"},{"id":"5762b5fe315cde9c16ce41de","name":"Mitch Albom"},{"id":"5762b5fe315cde9c16ce41df","name":"Sugababes"},{"id":"5762b5fe315cde9c16ce41e0","name":"Debut albums"},{"id":"5762b5fe315cde9c16ce41e1","name":"Gratitude"},{"id":"5762b5fe315cde9c16ce41e2","name":"tragedy"},{"id":"5762b5fe315cde9c16ce41e3","name":"gratitude"},{"id":"5762b5fe315cde9c16ce41e4","name":"entire perspective"},{"id":"5762b5fe315cde9c16ce41e5","name":"novel Tuesdays"},{"id":"5762b5fe315cde9c16ce41e6","name":"challenge"},{"id":"5762b5fe315cde9c16ce41e7","name":"people"},{"id":"5762b5fe315cde9c16ce41e8","name":"way"},{"id":"5762b5fe315cde9c16ce41e9","name":"Morrie"},{"id":"5762b5fe315cde9c16ce41ea","name":"darkness"},{"id":"5762b5fe315cde9c16ce41eb","name":"conjunction"},{"id":"5762b5fe315cde9c16ce41ec","name":"attitude"},{"id":"5762b5fe315cde9c16ce41ed","name":"question"},{"id":"5762b5fe315cde9c16ce41ee","name":"life"},{"id":"5762b5fe315cde9c16ce41ef","name":"light"},{"id":"5762b5fe315cde9c16ce41f0","name":"beauty"},{"id":"5762b5fe315cde9c16ce41f1","name":"lives"}],"guides":[]},{"id":"5762b515cde9c16ce41dc","title":"Find gratitude in life especially during a tragedy.","bigIdea":"Gratitude","essentialQuestion":"How can gratitude change my entire perspective on tragedy?","createdAt":"2016-06-16T14:21:49.076Z","updatedAt":"2016-06-16T14:21:49.076Z","user":{"id":"57616a22ee7e776c02f36586","picture":"https://gravatar.com/avatar/e0675d18aada9669f5db696e50f2f0d0?d=identicon"},"users":["57616a22ee7e776c02f36586"],"photo":{"large":{"height":"683","src":"https://farm6.staticflickr.com/5158/14437506753_4f9e839c33_b.jpg","width":"1024"},"medium":{"height":"333","src":"https://farm6.staticflickr.com/5158/14437506753_4f9e839c33.jpg","width":"500"},"owner":"Puno3000","small":{"height":"160","src":"https://farm6.staticflickr.com/5158/14437506753_4f9e839c33_m.jpg","width":"240"},"url":"https://www.flickr.com/photos/52782782@N08/14437506753"},"tags":[{"id":"5762b5fe315cde9c16ce41dd","name":"Tuesdays with Morrie"},{"id":"5762b5fe315cde9c16ce41de","name":"Mitch Albom"},{"id":"5762b5fe315cde9c16ce41df","name":"Sugababes"},{"id":"5762b5fe315cde9c16ce41e0","name":"Debut albums"},{"id":"5762b5fe315cde9c16ce41e1","name":"Gratitude"},{"id":"5762b5fe315cde9c16ce41e2","name":"tragedy"},{"id":"5762b5fe315cde9c16ce41e3","name":"gratitude"},{"id":"5762b5fe315cde9c16ce41e4","name":"entire perspective"},{"id":"5762b5fe315cde9c16ce41e5","name":"novel Tuesdays"},{"id":"5762b5fe315cde9c16ce41e6","name":"challenge"},{"id":"5762b5fe315cde9c16ce41e7","name":"people"},{"id":"5762b5fe315cde9c16ce41e8","name":"way"},{"id":"5762b5fe315cde9c16ce41e9","name":"Morrie"},{"id":"5762b5fe315cde9c16ce41ea","name":"darkness"},{"id":"5762b5fe315cde9c16ce41eb","name":"conjunction"},{"id":"5762b5fe315cde9c16ce41ec","name":"attitude"},{"id":"5762b5fe315cde9c16ce41ed","name":"question"},{"id":"5762b5fe315cde9c16ce41ee","name":"life"},{"id":"5762b5fe315cde9c16ce41ef","name":"light"},{"id":"5762b5fe315cde9c16ce41f0","name":"beauty"},{"id":"5762b5fe315cde9c16ce41f1","name":"lives"}],"guides":[]},{"id":"576dsadsa2b5fd315cde9c16ce41dc","title":"Find gratitude in life especially during a tragedy.","bigIdea":"Gratitude","essentialQuestion":"How can gratitude change my entire perspective on tragedy?","createdAt":"2016-06-16T14:21:49.076Z","updatedAt":"2016-06-16T14:21:49.076Z","user":{"id":"57616a22ee7e776c02f36586","picture":"https://gravatar.com/avatar/e0675d18aada9669f5db696e50f2f0d0?d=identicon"},"users":["57616a22ee7e776c02f36586"],"photo":{"large":{"height":"683","src":"https://farm6.staticflickr.com/5158/14437506753_4f9e839c33_b.jpg","width":"1024"},"medium":{"height":"333","src":"https://farm6.staticflickr.com/5158/14437506753_4f9e839c33.jpg","width":"500"},"owner":"Puno3000","small":{"height":"160","src":"https://farm6.staticflickr.com/5158/14437506753_4f9e839c33_m.jpg","width":"240"},"url":"https://www.flickr.com/photos/52782782@N08/14437506753"},"tags":[{"id":"5762b5fe315cde9c16ce41dd","name":"Tuesdays with Morrie"},{"id":"5762b5fe315cde9c16ce41de","name":"Mitch Albom"},{"id":"5762b5fe315cde9c16ce41df","name":"Sugababes"},{"id":"5762b5fe315cde9c16ce41e0","name":"Debut albums"},{"id":"5762b5fe315cde9c16ce41e1","name":"Gratitude"},{"id":"5762b5fe315cde9c16ce41e2","name":"tragedy"},{"id":"5762b5fe315cde9c16ce41e3","name":"gratitude"},{"id":"5762b5fe315cde9c16ce41e4","name":"entire perspective"},{"id":"5762b5fe315cde9c16ce41e5","name":"novel Tuesdays"},{"id":"5762b5fe315cde9c16ce41e6","name":"challenge"},{"id":"5762b5fe315cde9c16ce41e7","name":"people"},{"id":"5762b5fe315cde9c16ce41e8","name":"way"},{"id":"5762b5fe315cde9c16ce41e9","name":"Morrie"},{"id":"5762b5fe315cde9c16ce41ea","name":"darkness"},{"id":"5762b5fe315cde9c16ce41eb","name":"conjunction"},{"id":"5762b5fe315cde9c16ce41ec","name":"attitude"},{"id":"5762b5fe315cde9c16ce41ed","name":"question"},{"id":"5762b5fe315cde9c16ce41ee","name":"life"},{"id":"5762b5fe315cde9c16ce41ef","name":"light"},{"id":"5762b5fe315cde9c16ce41f0","name":"beauty"},{"id":"5762b5fe315cde9c16ce41f1","name":"lives"}],"guides":[]},{"id":"5762b5fd3dsaddsa15cde9c16ce41dc","title":"Find gratitude in life especially during a tragedy.","bigIdea":"Gratitude","essentialQuestion":"How can gratitude change my entire perspective on tragedy?","createdAt":"2016-06-16T14:21:49.076Z","updatedAt":"2016-06-16T14:21:49.076Z","user":{"id":"57616a22ee7e776c02f36586","picture":"https://gravatar.com/avatar/e0675d18aada9669f5db696e50f2f0d0?d=identicon"},"users":["57616a22ee7e776c02f36586"],"photo":{"large":{"height":"683","src":"https://farm6.staticflickr.com/5158/14437506753_4f9e839c33_b.jpg","width":"1024"},"medium":{"height":"333","src":"https://farm6.staticflickr.com/5158/14437506753_4f9e839c33.jpg","width":"500"},"owner":"Puno3000","small":{"height":"160","src":"https://farm6.staticflickr.com/5158/14437506753_4f9e839c33_m.jpg","width":"240"},"url":"https://www.flickr.com/photos/52782782@N08/14437506753"},"tags":[{"id":"5762b5fe315cde9c16ce41dd","name":"Tuesdays with Morrie"},{"id":"5762b5fe315cde9c16ce41de","name":"Mitch Albom"},{"id":"5762b5fe315cde9c16ce41df","name":"Sugababes"},{"id":"5762b5fe315cde9c16ce41e0","name":"Debut albums"},{"id":"5762b5fe315cde9c16ce41e1","name":"Gratitude"},{"id":"5762b5fe315cde9c16ce41e2","name":"tragedy"},{"id":"5762b5fe315cde9c16ce41e3","name":"gratitude"},{"id":"5762b5fe315cde9c16ce41e4","name":"entire perspective"},{"id":"5762b5fe315cde9c16ce41e5","name":"novel Tuesdays"},{"id":"5762b5fe315cde9c16ce41e6","name":"challenge"},{"id":"5762b5fe315cde9c16ce41e7","name":"people"},{"id":"5762b5fe315cde9c16ce41e8","name":"way"},{"id":"5762b5fe315cde9c16ce41e9","name":"Morrie"},{"id":"5762b5fe315cde9c16ce41ea","name":"darkness"},{"id":"5762b5fe315cde9c16ce41eb","name":"conjunction"},{"id":"5762b5fe315cde9c16ce41ec","name":"attitude"},{"id":"5762b5fe315cde9c16ce41ed","name":"question"},{"id":"5762b5fe315cde9c16ce41ee","name":"life"},{"id":"5762b5fe315cde9c16ce41ef","name":"light"},{"id":"5762b5fe315cde9c16ce41f0","name":"beauty"},{"id":"5762b5fe315cde9c16ce41f1","name":"lives"}],"guides":[]},{"id":"55fd315cde9c16ce41dc","title":"Find gratitude in life especially during a tragedy.","bigIdea":"Gratitude","essentialQuestion":"How can gratitude change my entire perspective on tragedy?","createdAt":"2016-06-16T14:21:49.076Z","updatedAt":"2016-06-16T14:21:49.076Z","user":{"id":"57616a22ee7e776c02f36586","picture":"https://gravatar.com/avatar/e0675d18aada9669f5db696e50f2f0d0?d=identicon"},"users":["57616a22ee7e776c02f36586"],"photo":{"large":{"height":"683","src":"https://farm6.staticflickr.com/5158/14437506753_4f9e839c33_b.jpg","width":"1024"},"medium":{"height":"333","src":"https://farm6.staticflickr.com/5158/14437506753_4f9e839c33.jpg","width":"500"},"owner":"Puno3000","small":{"height":"160","src":"https://farm6.staticflickr.com/5158/14437506753_4f9e839c33_m.jpg","width":"240"},"url":"https://www.flickr.com/photos/52782782@N08/14437506753"},"tags":[{"id":"5762b5fe315cde9c16ce41dd","name":"Tuesdays with Morrie"},{"id":"5762b5fe315cde9c16ce41de","name":"Mitch Albom"},{"id":"5762b5fe315cde9c16ce41df","name":"Sugababes"},{"id":"5762b5fe315cde9c16ce41e0","name":"Debut albums"},{"id":"5762b5fe315cde9c16ce41e1","name":"Gratitude"},{"id":"5762b5fe315cde9c16ce41e2","name":"tragedy"},{"id":"5762b5fe315cde9c16ce41e3","name":"gratitude"},{"id":"5762b5fe315cde9c16ce41e4","name":"entire perspective"},{"id":"5762b5fe315cde9c16ce41e5","name":"novel Tuesdays"},{"id":"5762b5fe315cde9c16ce41e6","name":"challenge"},{"id":"5762b5fe315cde9c16ce41e7","name":"people"},{"id":"5762b5fe315cde9c16ce41e8","name":"way"},{"id":"5762b5fe315cde9c16ce41e9","name":"Morrie"},{"id":"5762b5fe315cde9c16ce41ea","name":"darkness"},{"id":"5762b5fe315cde9c16ce41eb","name":"conjunction"},{"id":"5762b5fe315cde9c16ce41ec","name":"attitude"},{"id":"5762b5fe315cde9c16ce41ed","name":"question"},{"id":"5762b5fe315cde9c16ce41ee","name":"life"},{"id":"5762b5fe315cde9c16ce41ef","name":"light"},{"id":"5762b5fe315cde9c16ce41f0","name":"beauty"},{"id":"5762b5fe315cde9c16ce41f1","name":"lives"}],"guides":[]},{"id":"5762b5fd315cde9c16ce41dc23214","title":"Find gratitude in life especially during a tragedy.","bigIdea":"Gratitude","essentialQuestion":"How can gratitude change my entire perspective on tragedy?","createdAt":"2016-06-16T14:21:49.076Z","updatedAt":"2016-06-16T14:21:49.076Z","user":{"id":"57616a22ee7e776c02f36586","picture":"https://gravatar.com/avatar/e0675d18aada9669f5db696e50f2f0d0?d=identicon"},"users":["57616a22ee7e776c02f36586"],"photo":{"large":{"height":"683","src":"https://farm6.staticflickr.com/5158/14437506753_4f9e839c33_b.jpg","width":"1024"},"medium":{"height":"333","src":"https://farm6.staticflickr.com/5158/14437506753_4f9e839c33.jpg","width":"500"},"owner":"Puno3000","small":{"height":"160","src":"https://farm6.staticflickr.com/5158/14437506753_4f9e839c33_m.jpg","width":"240"},"url":"https://www.flickr.com/photos/52782782@N08/14437506753"},"tags":[{"id":"5762b5fe315cde9c16ce41dd","name":"Tuesdays with Morrie"},{"id":"5762b5fe315cde9c16ce41de","name":"Mitch Albom"},{"id":"5762b5fe315cde9c16ce41df","name":"Sugababes"},{"id":"5762b5fe315cde9c16ce41e0","name":"Debut albums"},{"id":"5762b5fe315cde9c16ce41e1","name":"Gratitude"},{"id":"5762b5fe315cde9c16ce41e2","name":"tragedy"},{"id":"5762b5fe315cde9c16ce41e3","name":"gratitude"},{"id":"5762b5fe315cde9c16ce41e4","name":"entire perspective"},{"id":"5762b5fe315cde9c16ce41e5","name":"novel Tuesdays"},{"id":"5762b5fe315cde9c16ce41e6","name":"challenge"},{"id":"5762b5fe315cde9c16ce41e7","name":"people"},{"id":"5762b5fe315cde9c16ce41e8","name":"way"},{"id":"5762b5fe315cde9c16ce41e9","name":"Morrie"},{"id":"5762b5fe315cde9c16ce41ea","name":"darkness"},{"id":"5762b5fe315cde9c16ce41eb","name":"conjunction"},{"id":"5762b5fe315cde9c16ce41ec","name":"attitude"},{"id":"5762b5fe315cde9c16ce41ed","name":"question"},{"id":"5762b5fe315cde9c16ce41ee","name":"life"},{"id":"5762b5fe315cde9c16ce41ef","name":"light"},{"id":"5762b5fe315cde9c16ce41f0","name":"beauty"},{"id":"5762b5fe315cde9c16ce41f1","name":"lives"}],"guides":[]},{"id":"5762b5fd315cde9c16ce41dc6565656","title":"Find gratitude in life especially during a tragedy.","bigIdea":"Gratitude","essentialQuestion":"How can gratitude change my entire perspective on tragedy?","createdAt":"2016-06-16T14:21:49.076Z","updatedAt":"2016-06-16T14:21:49.076Z","user":{"id":"57616a22ee7e776c02f36586","picture":"https://gravatar.com/avatar/e0675d18aada9669f5db696e50f2f0d0?d=identicon"},"users":["57616a22ee7e776c02f36586"],"photo":{"large":{"height":"683","src":"https://farm6.staticflickr.com/5158/14437506753_4f9e839c33_b.jpg","width":"1024"},"medium":{"height":"333","src":"https://farm6.staticflickr.com/5158/14437506753_4f9e839c33.jpg","width":"500"},"owner":"Puno3000","small":{"height":"160","src":"https://farm6.staticflickr.com/5158/14437506753_4f9e839c33_m.jpg","width":"240"},"url":"https://www.flickr.com/photos/52782782@N08/14437506753"},"tags":[{"id":"5762b5fe315cde9c16ce41dd","name":"Tuesdays with Morrie"},{"id":"5762b5fe315cde9c16ce41de","name":"Mitch Albom"},{"id":"5762b5fe315cde9c16ce41df","name":"Sugababes"},{"id":"5762b5fe315cde9c16ce41e0","name":"Debut albums"},{"id":"5762b5fe315cde9c16ce41e1","name":"Gratitude"},{"id":"5762b5fe315cde9c16ce41e2","name":"tragedy"},{"id":"5762b5fe315cde9c16ce41e3","name":"gratitude"},{"id":"5762b5fe315cde9c16ce41e4","name":"entire perspective"},{"id":"5762b5fe315cde9c16ce41e5","name":"novel Tuesdays"},{"id":"5762b5fe315cde9c16ce41e6","name":"challenge"},{"id":"5762b5fe315cde9c16ce41e7","name":"people"},{"id":"5762b5fe315cde9c16ce41e8","name":"way"},{"id":"5762b5fe315cde9c16ce41e9","name":"Morrie"},{"id":"5762b5fe315cde9c16ce41ea","name":"darkness"},{"id":"5762b5fe315cde9c16ce41eb","name":"conjunction"},{"id":"5762b5fe315cde9c16ce41ec","name":"attitude"},{"id":"5762b5fe315cde9c16ce41ed","name":"question"},{"id":"5762b5fe315cde9c16ce41ee","name":"life"},{"id":"5762b5fe315cde9c16ce41ef","name":"light"},{"id":"5762b5fe315cde9c16ce41f0","name":"beauty"},{"id":"5762b5fe315cde9c16ce41f1","name":"lives"}],"guides":[]},{"id":"5762a685ee7e776c02f3658f","title":"Be happy","bigIdea":"Happiness","essentialQuestion":"What if you could do anything you want to?","createdAt":"2016-06-16T13:15:49.419Z","updatedAt":"2016-06-16T13:15:49.419Z","user":{"id":"57616a22ee7e776c02f36586","picture":"https://gravatar.com/avatar/e0675d18aada9669f5db696e50f2f0d0?d=identicon"},"users":["57616a22ee7e776c02f36586"],"tags":[{"id":"5762a686ee7e776c02f36590","name":"Happiness"}],"guides":[]}]
